llmscraper/__init__.py
llmscraper/cleanup.py
llmscraper/models.py
llmscraper/preprocess.py
llmscraper-0.1.0.dist-info/METADATA
llmscraper-0.1.0.dist-info/WHEEL
llmscraper-0.1.0.dist-info/licenses/LICENSE
llmscraper-0.1.0.dist-info/RECORD
