Metadata-Version: 2.4
Name: llmscraper
Version: 0.1.0
Summary: LLM-powered web scraping in Python
Author-email: defisapiens <defisapiens@protonmail.com>
License-File: LICENSE
Requires-Python: >=3.9
Requires-Dist: beautifulsoup4>=4.12.3
Requires-Dist: google-genai>=1.24.0
Requires-Dist: html2text>=2024.2.26
Requires-Dist: instructor>=1.9.0
Requires-Dist: openai>=1.35.3
Requires-Dist: playwright>=1.44.0
Requires-Dist: pydantic>=2.7.4
